munits/__init__.py
munits/data.py
munits/us.py
munits/si/__init__.py
munits/si/prefix.py
munits-1.0.0.dist-info/LICENSE
munits-1.0.0.dist-info/METADATA
munits-1.0.0.dist-info/WHEEL
munits-1.0.0.dist-info/top_level.txt
munits-1.0.0.dist-info/RECORD
