Metadata-Version: 2.1
Name: munits
Version: 1.0.0
Summary: Multiplication-based units for Python
Home-page: https://github.com/DigitalDetective47/munits
Author: DigitalDetective47
Author-email: ninji2701@gmail.com
Project-URL: Bug Tracker, https://github.com/DigitalDetective47/munits/issues
Keywords: units
Classifier: Development Status :: 5 - Production/Stable
Classifier: License :: OSI Approved :: The Unlicense (Unlicense)
Classifier: Operating System :: OS Independent
Classifier: Programming Language :: Python :: 3
Classifier: Programming Language :: Python :: 3 :: Only
Classifier: Programming Language :: Python :: 3.11
Classifier: Programming Language :: Python :: 3.12
Classifier: Topic :: Scientific/Engineering
Classifier: Typing :: Typed
Requires-Python: >=3.11
License-File: LICENSE
